wantstoparty/__init__.py
wantstoparty/api.py
wantstoparty/checks.py
wantstoparty/errors.py
wantstoparty/http.py
wantstoparty/objects.py
wantstoparty/utils.py
wantstoparty/wtp.py
wantstoparty/_async/__init__.py
wantstoparty/_async/async_wtp.py
wantstoparty/oauth/__init__.py
wantstoparty/oauth/oauth.py
wantstoparty-2.1.3.dist-info/LICENSE.txt
wantstoparty-2.1.3.dist-info/METADATA
wantstoparty-2.1.3.dist-info/WHEEL
wantstoparty-2.1.3.dist-info/top_level.txt
wantstoparty-2.1.3.dist-info/RECORD
