Metadata-Version: 2.1
Name: wantstoparty
Version: 2.1.3
Summary: An API wrapper for the wants-to.party API.
Home-page: https://github.com/acatiadroid/wantstoparty
Author: acatiadroid
Author-email: <acatia@mail.com>
License: The MIT License (MIT)
Keywords: python,api wrapper
Classifier: Development Status :: 5 - Production/Stable
Classifier: Intended Audience :: Developers
Classifier: Programming Language :: Python :: 3
Classifier: Operating System :: Unix
Classifier: Operating System :: MacOS :: MacOS X
Classifier: Operating System :: Microsoft :: Windows
License-File: LICENSE.txt
Requires-Dist: aiohttp
Requires-Dist: requests
